Metadata-Version: 2.4
Name: fei-ws
Version: 2.1.0
Summary: Wrapper for the FEI Web Services v1.2 and FEI Entry System v3
Author-email: "Arend H. Tolner" <arie@scgvisual.com>
License: MPL-2.0
Project-URL: Homepage, https://github.com/Bounder/python-fei-ws
Keywords: fei,webservice,client
Classifier: Development Status :: 5 - Production/Stable
Classifier: Intended Audience :: Developers
Classifier: Topic :: Software Development :: Libraries
Classifier: License :: OSI Approved :: Mozilla Public License 2.0 (MPL 2.0)
Classifier: Programming Language :: Python :: 3.9
Classifier: Programming Language :: Python :: 3.10
Classifier: Programming Language :: Python :: 3.11
Classifier: Programming Language :: Python :: 3.12
Requires-Python: >=3.8
License-File: LICENSE.txt
Requires-Dist: requests>=2.32.4
Requires-Dist: zeep>=4.3.1
Dynamic: license-file
